telegram_objects/__init__.py
telegram_objects/admin.py
telegram_objects/api.py
telegram_objects/help_text.py
telegram_objects/models.py
telegram_objects/management/__init__.py
telegram_objects/management/commands/__init__.py
telegram_objects/management/commands/get_updates.py
telegram_objects/migrations/0001_initial.py
telegram_objects/migrations/__init__.py
django_telegram_objects-0.0.2.dist-info/LICENSE
django_telegram_objects-0.0.2.dist-info/METADATA
django_telegram_objects-0.0.2.dist-info/WHEEL
django_telegram_objects-0.0.2.dist-info/top_level.txt
django_telegram_objects-0.0.2.dist-info/RECORD
