Metadata-Version: 2.1
Name: django-telegram-objects
Version: 0.0.2
Summary: django-telegram-objects is a Django application that creates Telegram objects of a bot in a Postgres Database.
Home-page: https://github.com/ramiboutas/django-telegram-objects
Author: Rami Boutassghount
Author-email: ramiboutas@protonmail.com
Maintainer: Rami Boutassghount
Maintainer-email: ramiboutas@protonmail.com
License: MIT License
Project-URL: Changelog, https://github.com/ramiboutas/django-telegram-objects/blob/master/HISTORY.rst
Project-URL: Twitter, https://twitter.com/ramiboutas
Keywords: django,telegram,telegram-bot,bot,postgres
Platform: UNKNOWN
Classifier: Development Status :: 2 - Pre-Alpha
Classifier: Environment :: Web Environment
Classifier: Framework :: Django
Classifier: Framework :: Django :: 3.2
Classifier: Framework :: Django :: 4.0
Classifier: Framework :: Django :: 4.1
Classifier: Intended Audience :: Developers
Classifier: License :: OSI Approved :: BSD License
Classifier: Natural Language :: English
Classifier: Operating System :: OS Independent
Classifier: Programming Language :: Python :: 3 :: Only
Classifier: Programming Language :: Python :: 3
Classifier: Programming Language :: Python :: 3.7
Classifier: Programming Language :: Python :: 3.8
Classifier: Programming Language :: Python :: 3.9
Classifier: Programming Language :: Python :: 3.10
Classifier: Programming Language :: Python :: 3.11
Requires-Python: >=3.7
Requires-Dist: Django (>=3.2)
